{"version":1,"resource":"file:///home/ed/projects/takeup/stan_models/sbc_struct_data.stan","entries":[{"id":"qEHS.stan","timestamp":1657293855141},{"id":"rsC6.stan","timestamp":1657294337322},{"id":"D79H.stan","timestamp":1657294623978},{"id":"yItZ.stan","timestamp":1657706123590},{"id":"6AKg.stan","timestamp":1657708088774},{"id":"0dti.stan","timestamp":1657711035533},{"id":"qYeX.stan","timestamp":1657711098261},{"id":"gG3Z.stan","timestamp":1657711630302},{"id":"0tlN.stan","timestamp":1657711658405},{"id":"DhQP.stan","timestamp":1657712215741},{"id":"oIMy.stan","timestamp":1657712238301},{"id":"qkA8.stan","timestamp":1657712287882},{"id":"uMUD.stan","timestamp":1657712326759},{"id":"ENMH.stan","timestamp":1657712370243},{"id":"kl0c.stan","timestamp":1657712421873},{"id":"KmrQ.stan","timestamp":1657715327878},{"id":"1Zk0.stan","timestamp":1657715352065},{"id":"21MB.stan","timestamp":1657715407623},{"id":"zHMS.stan","timestamp":1657715461157},{"id":"Rx6P.stan","timestamp":1657715530951},{"id":"PDX2.stan","timestamp":1657715775141},{"id":"vG20.stan","timestamp":1657716126623},{"id":"HLB6.stan","timestamp":1657716153738},{"id":"i0P6.stan","timestamp":1657716182064},{"id":"vGsN.stan","timestamp":1657716235699},{"id":"llvO.stan","timestamp":1657716400874},{"id":"557J.stan","timestamp":1657716807198},{"id":"Sozf.stan","timestamp":1657716846347},{"id":"7eIV.stan","timestamp":1657716920710},{"id":"NNSh.stan","timestamp":1657717626909},{"id":"UwFX.stan","timestamp":1657717808395},{"id":"4LIf.stan","timestamp":1657717829165},{"id":"3d0h.stan","timestamp":1657717971852},{"id":"BSmv.stan","timestamp":1657718012070},{"id":"5j4K.stan","timestamp":1657719175781},{"id":"uvyA.stan","timestamp":1657719466818},{"id":"g1z7.stan","timestamp":1657719555627},{"id":"QwOz.stan","timestamp":1657719637228},{"id":"WvRU.stan","timestamp":1657721462101},{"id":"8qU0.stan","timestamp":1657721548185},{"id":"dbW3.stan","timestamp":1657721701247},{"id":"Gaxo.stan","timestamp":1657722691519},{"id":"Zh9V.stan","timestamp":1657733823602},{"id":"kZz5.stan","timestamp":1657733850435},{"id":"JYJ7.stan","timestamp":1657733954176},{"id":"HZtt.stan","timestamp":1657734141303},{"id":"jIDh.stan","timestamp":1657895107593},{"id":"8wXt.stan","timestamp":1657895135700},{"id":"Ie1y.stan","timestamp":1657896076037},{"id":"vJRI.stan","timestamp":1657903351139}]}