{"version":1,"resource":"file:///home/ed/projects/avoidance-power-calcs/shiny/arm-proportions.R","entries":[{"id":"ikHL.R","timestamp":1656403756365},{"id":"930r.R","timestamp":1656403974904},{"id":"Z1Qj.R","timestamp":1656404214596},{"id":"DxWF.R","timestamp":1656404291167},{"id":"0dh9.R","timestamp":1656404314034},{"id":"8LGx.R","timestamp":1656404331011},{"id":"2Y2f.R","timestamp":1656404945347},{"id":"rycS.R","timestamp":1656404978493},{"id":"2tnV.R","timestamp":1656404996163},{"id":"yg2f.R","timestamp":1656405062311},{"id":"9NK4.R","timestamp":1656518522598}]}